[
	{
		"__TYPE__": "SharedSliceContent",
		"variation": "default",
		"primary": {
			"titre": {
				"__TYPE__": "FieldContent",
				"value": "forgotten",
				"type": "Text"
			}
		},
		"items": [
			{
				"__TYPE__": "GroupItemContent",
				"value": [
					[
						"titre",
						{
							"__TYPE__": "FieldContent",
							"value": "keep",
							"type": "Text"
						}
					],
					[
						"document",
						{
							"__TYPE__": "LinkContent",
							"value": {
								"__TYPE__": "ExternalLink",
								"url": "https://slicemachine.dev"
							}
						}
					]
				]
			}
		]
	}
]