{
  "id": "document",
  "type": "SharedSlice",
  "name": "Document",
  "description": "Document",
  "variations": [
    {
      "id": "default",
      "name": "Default",
      "docURL": "...",
      "version": "initial",
      "description": "Default",
      "imageUrl": "",
      "primary": {
        "titre": {
          "type": "Text",
          "config": {
            "label": "Titre",
            "placeholder": ""
          }
        }
      },
      "items": {
        "titre": {
          "type": "Text",
          "config": {
            "label": "Titre",
            "placeholder": ""
          }
        },
        "document": {
          "type": "Link",
          "config": {
            "label": "Document",
            "placeholder": "",
            "select": null
          }
        }
      }
    }
  ]
}